README.md
setup.py
csr_aws_utils.egg-info/PKG-INFO
csr_aws_utils.egg-info/SOURCES.txt
csr_aws_utils.egg-info/dependency_links.txt
csr_aws_utils.egg-info/requires.txt
csr_aws_utils.egg-info/top_level.txt
csr_cloud/__init__.py
csr_cloud/as_aws.py
csr_cloud/csr_cloud.py
csr_cloud/ha_csr.py