Metadata-Version: 1.1
Name: csr-aws-utils
Version: 2.0.1
Summary: Utilities for csr1000v on AWS
Home-page: https://github4-chn.cisco.com/csr1000v-aws/csr_aws_utils
Author: Christopher Reder
Author-email: creder@cisco.com
License: MIT
Download-URL: https://github4-chn.cisco.com/csr1000v-aws/csr_aws_utils/archive/2.0.1.tar.gz
Keywords: cisco,aws,guestshell,csr1000v
Platform: UNKNOWN
